{
  "pageMetadata": {
    "url": "https://blucheez.fashion/search?q=kurta&type=product",
    "title": "Search results: 103 Search Results for: “kurta” – Blucheez",
    "searchQuery": "",
    "totalResults": 0,
    "productsDisplayed": 21,
    "hasMoreProducts": true,
    "percentageLoaded": 19.4175
  },
  "products": [
    {
      "index": 1,
      "productId": "7210939482307",
      "handle": "round-hem-printed-kurti",
      "title": "ROUND HEM PRINTED KURTI",
      "url": "/products/round-hem-printed-kurti?_pos=1&_sid=42d271b2b&_ss=r",
      "imageUrl": "//blucheez.fashion/cdn/shop/products/round-hem-printed-kurti-blucheez-1-32115647545623.jpg",
      "available": true,
      "regularPrice": "Tk 1,695",
      "salePrice": "Tk 848",
      "compareAtPrice": "Tk 169500",
      "currentPrice": "Tk 84750",
      "variantCount": 0,
      "variants": []
    },
    {
      "index": 2,
      "productId": "9119215583511",
      "handle": "essential-kurti",
      "title": "ESSENTIAL KURTI",
      "url": "/products/essential-kurti?_pos=2&_sid=42d271b2b&_ss=r",
      "imageUrl": "//blucheez.fashion/cdn/shop/files/WKL-122PS-01.webp",
      "available": true,
      "regularPrice": "Tk 1,995",
      "salePrice": "Tk 998",
      "compareAtPrice": "Tk 199500",
      "currentPrice": "Tk 99750",
      "variantCount": 0,
      "variants": []
    },
    {
      "index": 3,
      "productId": "9073891344663",
      "handle": "embroidered-kurti-2",
      "title": "EMBROIDERED KURTI",
      "url": "/products/embroidered-kurti-2?_pos=3&_sid=42d271b2b&_ss=r",
      "imageUrl": "//blucheez.fashion/cdn/shop/files/WKL-099-P-WEB-01.webp",
      "available": true,
      "regularPrice": "Tk 1,995",
      "salePrice": "Tk 998",
      "compareAtPrice": "Tk 199500",
      "currentPrice": "Tk 99750",
      "variantCount": 0,
      "variants": []
    },
    {
      "index": 4,
      "productId": "9852207792407",
      "handle": "printed-kurti-5",
      "title": "PRINTED KURTI",
      "url": "/products/printed-kurti-5?_pos=4&_sid=42d271b2b&_ss=r",
      "imageUrl": "//blucheez.fashion/cdn/shop/files/WKL-146.webp",
      "available": true,
      "regularPrice": "Tk 1,995",
      "salePrice": "",
      "compareAtPrice": null,
      "currentPrice": "Tk 199500",
      "variantCount": 0,
      "variants": []
    },
    {
      "index": 5,
      "productId": "10037226733847",
      "handle": "printed-kurti-11",
      "title": "ONE PCS KURTI",
      "url": "/products/printed-kurti-11?_pos=5&_sid=42d271b2b&_ss=r",
      "imageUrl": "//blucheez.fashion/cdn/shop/files/WKL-196-BLACK-WEB-1.webp",
      "available": true,
      "regularPrice": "Tk 2,390",
      "salePrice": "",
      "compareAtPrice": null,
      "currentPrice": "Tk 239000",
      "variantCount": 0,
      "variants": []
    },
    {
      "index": 6,
      "productId": "9986442035479",
      "handle": "printed-kurti-10",
      "title": "PRINTED KURTI",
      "url": "/products/printed-kurti-10?_pos=6&_sid=42d271b2b&_ss=r",
      "imageUrl": "//blucheez.fashion/cdn/shop/files/162_895f9e46-a357-49a9-aa94-8f149f5bf681.webp",
      "available": true,
      "regularPrice": "Tk 2,295",
      "salePrice": "Tk 1,148",
      "compareAtPrice": "Tk 229500",
      "currentPrice": "Tk 114750",
      "variantCount": 0,
      "variants": []
    },
    {
      "index": 7,
      "productId": "9676406325527",
      "handle": "printed-kurti-4",
      "title": "PRINTED KURTI",
      "url": "/products/printed-kurti-4?_pos=7&_sid=42d271b2b&_ss=r",
      "imageUrl": "//blucheez.fashion/cdn/shop/files/1_8f59d723-3117-4cad-a272-d30d88912392.webp",
      "available": true,
      "regularPrice": "Tk 3,295",
      "salePrice": "Tk 1,648",
      "compareAtPrice": "Tk 329500",
      "currentPrice": "Tk 164750",
      "variantCount": 0,
      "variants": []
    },
    {
      "index": 8,
      "productId": "10037330018583",
      "handle": "premium-western-top-12",
      "title": "ONE PCS KURTI",
      "url": "/products/premium-western-top-12?_pos=8&_sid=42d271b2b&_ss=r",
      "imageUrl": "//blucheez.fashion/cdn/shop/files/WKL-216-PINK-WEB-01.webp",
      "available": true,
      "regularPrice": "Tk 2,390",
      "salePrice": "",
      "compareAtPrice": null,
      "currentPrice": "Tk 239000",
      "variantCount": 0,
      "variants": []
    },
    {
      "index": 9,
      "productId": "8979204636951",
      "handle": "embroidered-kameez-13",
      "title": "EMBROIDERED KAMEEZ",
      "url": "/products/embroidered-kameez-13?_pos=9&_sid=42d271b2b&_ss=r",
      "imageUrl": "//blucheez.fashion/cdn/shop/files/WKL-106P-WEB-1.webp",
      "available": true,
      "regularPrice": "Tk 2,395",
      "salePrice": "Tk 1,198",
      "compareAtPrice": "Tk 239500",
      "currentPrice": "Tk 119750",
      "variantCount": 0,
      "variants": []
    },
    {
      "index": 10,
      "productId": "7961814728983",
      "handle": "embroidered-solid-kameez-1",
      "title": "EMBROIDERED SOLID KAMEEZ",
      "url": "/products/embroidered-solid-kameez-1?_pos=10&_sid=42d271b2b&_ss=r",
      "imageUrl": "//blucheez.fashion/cdn/shop/products/EmbroideredKameez_3886f12b-5eb3-4483-a24c-672da7d27095.webp",
      "available": true,
      "regularPrice": "Tk 2,695",
      "salePrice": "Tk 1,348",
      "compareAtPrice": "Tk 269500",
      "currentPrice": "Tk 134750",
      "variantCount": 0,
      "variants": []
    },
    {
      "index": 11,
      "productId": "7446169354435",
      "handle": "zardozi-worked-printed-kimono-1",
      "title": "ZARDOZI WORKED PRINTED KIMONO",
      "url": "/products/zardozi-worked-printed-kimono-1?_pos=11&_sid=42d271b2b&_ss=r",
      "imageUrl": "//blucheez.fashion/cdn/shop/products/IMG_6558copy.webp",
      "available": true,
      "regularPrice": "Tk 3,995",
      "salePrice": "Tk 1,998",
      "compareAtPrice": "Tk 399500",
      "currentPrice": "Tk 199750",
      "variantCount": 0,
      "variants": []
    },
    {
      "index": 12,
      "productId": "10213469978903",
      "handle": "printed-zari-suit",
      "title": "PRINTED ZARI SUIT",
      "url": "/products/printed-zari-suit?_pos=12&_sid=42d271b2b&_ss=r",
      "imageUrl": "//blucheez.fashion/cdn/shop/files/80.jpg",
      "available": true,
      "regularPrice": "Tk 6,890",
      "salePrice": "",
      "compareAtPrice": null,
      "currentPrice": "Tk 689000",
      "variantCount": 0,
      "variants": []
    },
    {
      "index": 13,
      "productId": "10213472600343",
      "handle": "zari-set-1",
      "title": "ZARI SET",
      "url": "/products/zari-set-1?_pos=13&_sid=42d271b2b&_ss=r",
      "imageUrl": "//blucheez.fashion/cdn/shop/files/127.jpg",
      "available": true,
      "regularPrice": "Tk 4,890",
      "salePrice": "",
      "compareAtPrice": null,
      "currentPrice": "Tk 489000",
      "variantCount": 0,
      "variants": []
    },
    {
      "index": 14,
      "productId": "10172582494487",
      "handle": "zardosi-fusion-vest",
      "title": "ZARDOSI FUSION VEST",
      "url": "/products/zardosi-fusion-vest?_pos=14&_sid=42d271b2b&_ss=r",
      "imageUrl": "//blucheez.fashion/cdn/shop/files/BMV-046-DARKBROWN-WEB-01.webp",
      "available": true,
      "regularPrice": "Tk 8,490",
      "salePrice": "",
      "compareAtPrice": null,
      "currentPrice": "Tk 849000",
      "variantCount": 0,
      "variants": []
    },
    {
      "index": 15,
      "productId": "7446207594691",
      "handle": "puff-sleeve-wrap-dress-1",
      "title": "PUFF SLEEVE WRAP DRESS",
      "url": "/products/puff-sleeve-wrap-dress-1?_pos=15&_sid=42d271b2b&_ss=r",
      "imageUrl": "//blucheez.fashion/cdn/shop/products/IMG_6405copy.webp",
      "available": true,
      "regularPrice": "Tk 1,995",
      "salePrice": "Tk 998",
      "compareAtPrice": "Tk 199500",
      "currentPrice": "Tk 99750",
      "variantCount": 0,
      "variants": []
    },
    {
      "index": 16,
      "productId": "7446207529155",
      "handle": "puff-sleeve-wrap-dress",
      "title": "PUFF SLEEVE WRAP DRESS",
      "url": "/products/puff-sleeve-wrap-dress?_pos=16&_sid=42d271b2b&_ss=r",
      "imageUrl": "//blucheez.fashion/cdn/shop/products/IMG_6396copy.webp",
      "available": true,
      "regularPrice": "Tk 1,995",
      "salePrice": "Tk 998",
      "compareAtPrice": "Tk 199500",
      "currentPrice": "Tk 99750",
      "variantCount": 0,
      "variants": []
    },
    {
      "index": 17,
      "productId": "7316137476291",
      "handle": "shaded-kameez-2",
      "title": "SHADED KAMEEZ",
      "url": "/products/shaded-kameez-2?_pos=17&_sid=42d271b2b&_ss=r",
      "imageUrl": "//blucheez.fashion/cdn/shop/products/shaded-kameez-blucheez-1.jpg",
      "available": true,
      "regularPrice": "Tk 2,695",
      "salePrice": "Tk 1,348",
      "compareAtPrice": "Tk 269500",
      "currentPrice": "Tk 134750",
      "variantCount": 0,
      "variants": []
    },
    {
      "index": 18,
      "productId": "7316103790787",
      "handle": "shaded-kameez-1",
      "title": "SHADED KAMEEZ",
      "url": "/products/shaded-kameez-1?_pos=18&_sid=42d271b2b&_ss=r",
      "imageUrl": "//blucheez.fashion/cdn/shop/products/shaded-kameez-blucheez-1_26fca42d-a4b6-41bd-a68a-0bb55eb0f0ea.jpg",
      "available": true,
      "regularPrice": "Tk 2,695",
      "salePrice": "Tk 1,348",
      "compareAtPrice": "Tk 269500",
      "currentPrice": "Tk 134750",
      "variantCount": 0,
      "variants": []
    },
    {
      "index": 19,
      "productId": "8648321696023",
      "handle": "embroidered-kameez-7",
      "title": "EMBROIDERED KAMEEZ",
      "url": "/products/embroidered-kameez-7?_pos=19&_sid=42d271b2b&_ss=r",
      "imageUrl": "//blucheez.fashion/cdn/shop/files/IMG_5478.webp",
      "available": true,
      "regularPrice": "Tk 2,495",
      "salePrice": "Tk 1,248",
      "compareAtPrice": "Tk 249500",
      "currentPrice": "Tk 124750",
      "variantCount": 0,
      "variants": []
    },
    {
      "index": 20,
      "productId": "8647963509015",
      "handle": "embroidered-kameez-6",
      "title": "EMBROIDERED KAMEEZ",
      "url": "/products/embroidered-kameez-6?_pos=20&_sid=42d271b2b&_ss=r",
      "imageUrl": "//blucheez.fashion/cdn/shop/files/WKL-100BL-01.webp",
      "available": true,
      "regularPrice": "Tk 2,495",
      "salePrice": "Tk 1,248",
      "compareAtPrice": "Tk 249500",
      "currentPrice": "Tk 124750",
      "variantCount": 0,
      "variants": []
    },
    {
      "index": 21,
      "productId": null,
      "handle": null,
      "title": "",
      "url": "",
      "imageUrl": "",
      "available": null,
      "regularPrice": "",
      "salePrice": "",
      "compareAtPrice": null,
      "currentPrice": null,
      "variantCount": 0,
      "variants": []
    }
  ]
}